bpqcrypto-1.3.3.data/purelib/bpqcrypto/__init__.py
bpqcrypto-1.3.3.data/purelib/bpqcrypto/aes.py
bpqcrypto-1.3.3.data/purelib/bpqcrypto/bpqcrypto.dll
bpqcrypto-1.3.3.data/purelib/bpqcrypto/test.py
bpqcrypto-1.3.3.dist-info/LICENSE
bpqcrypto-1.3.3.dist-info/METADATA
bpqcrypto-1.3.3.dist-info/WHEEL
bpqcrypto-1.3.3.dist-info/top_level.txt
bpqcrypto-1.3.3.dist-info/RECORD
